azure/ai/anomalydetector/__init__.py
azure/ai/anomalydetector/_client.py
azure/ai/anomalydetector/_configuration.py
azure/ai/anomalydetector/_model_base.py
azure/ai/anomalydetector/_patch.py
azure/ai/anomalydetector/_serialization.py
azure/ai/anomalydetector/_vendor.py
azure/ai/anomalydetector/_version.py
azure/ai/anomalydetector/py.typed
azure/ai/anomalydetector/_operations/__init__.py
azure/ai/anomalydetector/_operations/_operations.py
azure/ai/anomalydetector/_operations/_patch.py
azure/ai/anomalydetector/aio/__init__.py
azure/ai/anomalydetector/aio/_client.py
azure/ai/anomalydetector/aio/_configuration.py
azure/ai/anomalydetector/aio/_patch.py
azure/ai/anomalydetector/aio/_vendor.py
azure/ai/anomalydetector/aio/_operations/__init__.py
azure/ai/anomalydetector/aio/_operations/_operations.py
azure/ai/anomalydetector/aio/_operations/_patch.py
azure/ai/anomalydetector/models/__init__.py
azure/ai/anomalydetector/models/_enums.py
azure/ai/anomalydetector/models/_models.py
azure/ai/anomalydetector/models/_patch.py
azure_ai_anomalydetector-3.0.0b6.dist-info/LICENSE
azure_ai_anomalydetector-3.0.0b6.dist-info/METADATA
azure_ai_anomalydetector-3.0.0b6.dist-info/WHEEL
azure_ai_anomalydetector-3.0.0b6.dist-info/top_level.txt
azure_ai_anomalydetector-3.0.0b6.dist-info/RECORD
